odoo/addons/l10n_it_split_payment/README.rst
odoo/addons/l10n_it_split_payment/__init__.py
odoo/addons/l10n_it_split_payment/__manifest__.py
odoo/addons/l10n_it_split_payment/i18n/ar.po
odoo/addons/l10n_it_split_payment/i18n/bg.po
odoo/addons/l10n_it_split_payment/i18n/bs.po
odoo/addons/l10n_it_split_payment/i18n/ca.po
odoo/addons/l10n_it_split_payment/i18n/cs.po
odoo/addons/l10n_it_split_payment/i18n/de.po
odoo/addons/l10n_it_split_payment/i18n/el_GR.po
odoo/addons/l10n_it_split_payment/i18n/en_GB.po
odoo/addons/l10n_it_split_payment/i18n/es.po
odoo/addons/l10n_it_split_payment/i18n/es_AR.po
odoo/addons/l10n_it_split_payment/i18n/es_CR.po
odoo/addons/l10n_it_split_payment/i18n/es_EC.po
odoo/addons/l10n_it_split_payment/i18n/es_MX.po
odoo/addons/l10n_it_split_payment/i18n/et.po
odoo/addons/l10n_it_split_payment/i18n/fi.po
odoo/addons/l10n_it_split_payment/i18n/fr.po
odoo/addons/l10n_it_split_payment/i18n/fr_CA.po
odoo/addons/l10n_it_split_payment/i18n/fr_CH.po
odoo/addons/l10n_it_split_payment/i18n/gl.po
odoo/addons/l10n_it_split_payment/i18n/hr.po
odoo/addons/l10n_it_split_payment/i18n/hr_HR.po
odoo/addons/l10n_it_split_payment/i18n/hu.po
odoo/addons/l10n_it_split_payment/i18n/id.po
odoo/addons/l10n_it_split_payment/i18n/it.po
odoo/addons/l10n_it_split_payment/i18n/ja.po
odoo/addons/l10n_it_split_payment/i18n/l10n_it_split_payment.pot
odoo/addons/l10n_it_split_payment/i18n/lt.po
odoo/addons/l10n_it_split_payment/i18n/mk.po
odoo/addons/l10n_it_split_payment/i18n/mn.po
odoo/addons/l10n_it_split_payment/i18n/nb.po
odoo/addons/l10n_it_split_payment/i18n/nb_NO.po
odoo/addons/l10n_it_split_payment/i18n/nl.po
odoo/addons/l10n_it_split_payment/i18n/nl_BE.po
odoo/addons/l10n_it_split_payment/i18n/pl.po
odoo/addons/l10n_it_split_payment/i18n/pt.po
odoo/addons/l10n_it_split_payment/i18n/pt_BR.po
odoo/addons/l10n_it_split_payment/i18n/pt_PT.po
odoo/addons/l10n_it_split_payment/i18n/ro.po
odoo/addons/l10n_it_split_payment/i18n/ru.po
odoo11_addon_l10n_it_split_payment-11.0.1.1.0.99.dev12.dist-info/METADATA
odoo11_addon_l10n_it_split_payment-11.0.1.1.0.99.dev12.dist-info/WHEEL
odoo11_addon_l10n_it_split_payment-11.0.1.1.0.99.dev12.dist-info/top_level.txt
odoo11_addon_l10n_it_split_payment-11.0.1.1.0.99.dev12.dist-info/RECORD
